barracuda_api/__init__.py
barracuda_api/barracuda.py
barracuda_api/endpoints.py
barracuda_api/exceptions.py
tests/__init__.py
tests/test_01_box_info.py
tests/test_02_ff_lists copy.py
tests/test_02_ff_lists.py
tests/test_03_ff_networks.py
tests/test_04_ff_services.py
tests/test_05_ff_rules.py
barracuda_api-0.4.dist-info/METADATA
barracuda_api-0.4.dist-info/WHEEL
barracuda_api-0.4.dist-info/top_level.txt
barracuda_api-0.4.dist-info/RECORD
