Metadata-Version: 2.1
Name: barracuda-api
Version: 0.4
Summary: Barracuda REST API abstraction
Home-page: 
Author: Peter Gastinger
Author-email: peter.gastinger@omv.com
Classifier: Programming Language :: Python :: 3
Classifier: Operating System :: OS Independent
Requires-Dist: requests
